aiotcloud/__init__.py
aiotcloud/pyaiot.py
aiotcloud/pyword.py
aiotcloud/fonts/ASC16_8
aiotcloud/fonts/ASC32_16
aiotcloud/fonts/HZK12
aiotcloud/fonts/HZK16
aiotcloud/rshell/__init__.py
aiotcloud/rshell/__main__.py
aiotcloud/rshell/command_line.py
aiotcloud/rshell/getch.py
aiotcloud/rshell/pyboard.py
aiotcloud/rshell/version.py
tech/aiotcloud/python/__init__.py
tech/aiotcloud/python/pyaiot.py
tech/aiotcloud/python/pyword.py
tech/aiotcloud/python/fonts/ASC16_8
tech/aiotcloud/python/fonts/ASC32_16
tech/aiotcloud/python/fonts/HZK12
tech/aiotcloud/python/fonts/HZK16
aiot_client-1.2.0.dist-info/METADATA
aiot_client-1.2.0.dist-info/WHEEL
aiot_client-1.2.0.dist-info/top_level.txt
aiot_client-1.2.0.dist-info/RECORD
