Metadata-Version: 2.1
Name: aiot-client
Version: 1.2.0
Summary: Ver1.2.0 修复repl导入包bug
Home-page: https://github.com/aiotcloud-tech/python-aiot-sdk
Author: sangxin
Author-email: 2876424407@qq.com
Maintainer: sangxin
Maintainer-email: 2876424407@qq.com
License: UNKNOWN
Platform: UNKNOWN
Requires-Dist: paho-mqtt
Requires-Dist: pyreadline
Requires-Dist: pyudev (>=0.16)
Requires-Dist: pyserial
Requires-Dist: six
